{"hash":"e82f1a30de7b9782d6dfcd80a368fca2d582e881","data":{"doc":{"title":"Pages","headings":[{"value":"Pages"}],"subtitles":[{"depth":1,"value":"Pages","anchor":"#pages"},{"depth":2,"value":"File-based pages","anchor":"#file-based-pages"},{"depth":2,"value":"Programmatic pages","anchor":"#programmatic-pages"},{"depth":2,"value":"Dynamic routing","anchor":"#dynamic-routing"},{"depth":2,"value":"Page meta info","anchor":"#page-meta-info"},{"depth":2,"value":"Custom 404 page","anchor":"#custom-404-page"}]}},"context":{}}